{
  "hash": "4afe9492",
  "configHash": "c9c364a0",
  "lockfileHash": "059c376c",
  "browserHash": "8ab50887",
  "optimized": {
    "react": {
      "src": "../../node_modules/react/index.js",
      "file": "react.js",
      "fileHash": "88b2f2ee",
      "needsInterop": true
    },
    "react-dom/client": {
      "src": "../../node_modules/react-dom/client.js",
      "file": "react-dom_client.js",
      "fileHash": "5ffac2e5",
      "needsInterop": true
    },
    "react-router-dom": {
      "src": "../../node_modules/react-router-dom/dist/index.js",
      "file": "react-router-dom.js",
      "fileHash": "4d6fc207",
      "needsInterop": false
    },
    "axios": {
      "src": "../../node_modules/axios/index.js",
      "file": "axios.js",
      "fileHash": "ec28f118",
      "needsInterop": false
    }
  },
  "chunks": {
    "chunk-PXJLUKTU": {
      "file": "chunk-PXJLUKTU.js"
    },
    "chunk-FQO5W7GE": {
      "file": "chunk-FQO5W7GE.js"
    },
    "chunk-ZS7NZCD4": {
      "file": "chunk-ZS7NZCD4.js"
    }
  }
}